main.py
source_goldcast/__init__.py
source_goldcast/manifest.yaml
source_goldcast/run.py
source_goldcast/schemas/event_agenda.json
source_goldcast/source.py
airbyte_source_goldcast-0.1.8.dist-info/METADATA
airbyte_source_goldcast-0.1.8.dist-info/WHEEL
airbyte_source_goldcast-0.1.8.dist-info/entry_points.txt
airbyte_source_goldcast-0.1.8.dist-info/RECORD
