Metadata-Version: 2.1
Name: airbyte-source-goldcast
Version: 0.1.8
Summary: Source implementation for goldcast.
Home-page: https://airbyte.com
License: MIT
Author: Airbyte
Author-email: contact@airbyte.io
Requires-Python: >=3.9,<3.12
Classifier: License :: OSI Approved :: MIT License
Classifier: Programming Language :: Python :: 3
Classifier: Programming Language :: Python :: 3.9
Classifier: Programming Language :: Python :: 3.10
Classifier: Programming Language :: Python :: 3.11
Requires-Dist: airbyte-cdk (<3)
Project-URL: Documentation, https://docs.airbyte.com/integrations/sources/goldcast
Project-URL: Repository, https://github.com/airbytehq/airbyte
